git_delete_merged_branches/__init__.py
git_delete_merged_branches/__main__.py
git_delete_merged_branches/_argparse_color.py
git_delete_merged_branches/_cli.py
git_delete_merged_branches/_confirm.py
git_delete_merged_branches/_engine.py
git_delete_merged_branches/_git.py
git_delete_merged_branches/_messenger.py
git_delete_merged_branches/_metadata.py
git_delete_merged_branches/_multiselect.py
git_delete_merged_branches/_shell.py
git_delete_merged_branches/tests/__init__.py
git_delete_merged_branches/tests/helpers.py
git_delete_merged_branches/tests/test_cli.py
git_delete_merged_branches/tests/test_engine.py
git_delete_merged_branches/tests/test_git.py
git_delete_merged_branches/tests/test_shell.py
git_delete_merged_branches-7.5.1.data/data/share/man/man1/git-delete-merged-branches.1
git_delete_merged_branches-7.5.1.data/data/share/man/man1/git-dmb.1
git_delete_merged_branches-7.5.1.dist-info/licenses/LICENSE
git_delete_merged_branches-7.5.1.dist-info/METADATA
git_delete_merged_branches-7.5.1.dist-info/WHEEL
git_delete_merged_branches-7.5.1.dist-info/entry_points.txt
git_delete_merged_branches-7.5.1.dist-info/top_level.txt
git_delete_merged_branches-7.5.1.dist-info/RECORD
